kensho/__init__.py
kensho-0.0.1.dist-info/METADATA
kensho-0.0.1.dist-info/WHEEL
kensho-0.0.1.dist-info/top_level.txt
kensho-0.0.1.dist-info/RECORD
