Metadata-Version: 2.4
Name: kensho
Version: 0.0.1
Summary: Reserved package name for the Kensho Health OS tooling.
Author: Scarlet Moore
License: MIT
Keywords: kensho,health,placeholder
Classifier: Programming Language :: Python :: 3
Classifier: Programming Language :: Python :: 3 :: Only
Classifier: License :: OSI Approved :: MIT License
Classifier: Operating System :: OS Independent
Requires-Python: >=3.9
